{"assets/images/back-icon.png":["assets/images/back-icon.png"],"assets/images/bell-01.png":["assets/images/bell-01.png"],"assets/images/book-closed.png":["assets/images/book-closed.png"],"assets/images/cert_download.png":["assets/images/cert_download.png"],"assets/images/certificate-01.png":["assets/images/certificate-01.png"],"assets/images/event_placeholder.png":["assets/images/event_placeholder.png"],"assets/images/home.png":["assets/images/home.png"],"assets/images/no-cert.png":["assets/images/no-cert.png"],"assets/images/placeholder.png":["assets/images/placeholder.png"],"assets/images/placeholder_login.png":["assets/images/placeholder_login.png"],"assets/images/profile-cert.png":["assets/images/profile-cert.png"],"assets/images/profile-exit.png":["assets/images/profile-exit.png"],"assets/images/profile-profile.png":["assets/images/profile-profile.png"],"assets/images/profile-translate.png":["assets/images/profile-translate.png"],"assets/images/profile.png":["assets/images/profile.png"],"assets/translations/en.json":["assets/translations/en.json"],"packages/cupertino_icons/assets/CupertinoIcons.ttf":["packages/cupertino_icons/assets/CupertinoIcons.ttf"]}